tike/__init__.py
tike/cluster.py
tike/constants.py
tike/linalg.py
tike/opt.py
tike/precision.py
tike/random.py
tike/scan.py
tike/trajectory.py
tike/view.py
tike/align/__init__.py
tike/align/align.py
tike/align/solvers/__init__.py
tike/align/solvers/cross_correlation.py
tike/align/solvers/farneback.py
tike/communicators/__init__.py
tike/communicators/comm.py
tike/communicators/mpi.py
tike/communicators/pool.py
tike/communicators/stream.py
tike/lamino/__init__.py
tike/lamino/bucket.py
tike/lamino/lamino.py
tike/lamino/solvers/__init__.py
tike/lamino/solvers/bucket.py
tike/lamino/solvers/cgrad.py
tike/operators/__init__.py
tike/operators/cupy/__init__.py
tike/operators/cupy/alignment.py
tike/operators/cupy/bucket.cu
tike/operators/cupy/bucket.py
tike/operators/cupy/cache.py
tike/operators/cupy/convolution.cu
tike/operators/cupy/convolution.py
tike/operators/cupy/flow.py
tike/operators/cupy/fresnelspectprop.py
tike/operators/cupy/grid.cu
tike/operators/cupy/interp.cu
tike/operators/cupy/lamino.py
tike/operators/cupy/multislice.py
tike/operators/cupy/objective.py
tike/operators/cupy/operator.py
tike/operators/cupy/pad.py
tike/operators/cupy/patch.py
tike/operators/cupy/propagation.py
tike/operators/cupy/ptycho.py
tike/operators/cupy/rotate.py
tike/operators/cupy/shift.py
tike/operators/cupy/usfft.cu
tike/operators/cupy/usfft.py
tike/ptycho/__init__.py
tike/ptycho/exitwave.py
tike/ptycho/fresnel.py
tike/ptycho/io.py
tike/ptycho/learn.py
tike/ptycho/object.py
tike/ptycho/position.py
tike/ptycho/probe.py
tike/ptycho/ptycho.py
tike/ptycho/solvers/__init__.py
tike/ptycho/solvers/_preconditioner.py
tike/ptycho/solvers/dm.py
tike/ptycho/solvers/lstsq.py
tike/ptycho/solvers/options.py
tike/ptycho/solvers/rpie.py
tike-0.26.0.dist-info/LICENSE
tike-0.26.0.dist-info/METADATA
tike-0.26.0.dist-info/WHEEL
tike-0.26.0.dist-info/top_level.txt
tike-0.26.0.dist-info/RECORD
