Metadata-Version: 2.1
Name: tike
Version: 0.26.0
Author: Xiaodong Yu, Viktor Nikitin, Ash Tripathi
Author-email: Doga Gursoy <dgursoy@anl.gov>, Daniel Ching <dching@anl.gov>
License: BSD 3-Clause License
Project-URL: docs, http://tike.readthedocs.org
Project-URL: source, http://github.com/tomography/tike.git
Classifier: Intended Audience :: Developers
Classifier: Intended Audience :: Science/Research
Classifier: License :: OSI Approved :: BSD License
Classifier: Natural Language :: English
Classifier: Operating System :: OS Independent
Classifier: Programming Language :: Python :: 3 :: Only
Classifier: Topic :: Scientific/Engineering
Requires-Python: ~=3.8
License-File: LICENSE
Requires-Dist: cupy !=10.3.0,!=13.0.*,>=10.0
Requires-Dist: matplotlib ==3.*
Requires-Dist: numpy ~=1.17
Requires-Dist: opencv-python <5.0,>=3.4
Requires-Dist: scipy >=1.6.0
Requires-Dist: importlib-resources ; python_version < "3.9"
Provides-Extra: mpi
Requires-Dist: mpi4py ==3.* ; extra == 'mpi'
